compose/__init__.py
compose/_internal.py
compose/asyncio.py
compose/concurrent.py
compose/constants.py
compose/container.py
compose/entity.py
compose/enums.py
compose/exceptions.py
compose/field.py
compose/func.py
compose/logging.py
compose/pagination.py
compose/py.typed
compose/settings.py
compose/stream.py
compose/typing.py
compose/utils.py
compose/auth/__init__.py
compose/auth/authorization_server.py
compose/auth/password.py
compose/auth/resource_server.py
compose/auth/token_decoder.py
compose/auth/token_issuer.py
compose/auth/vo.py
compose/aws/__init__.py
compose/aws/s3.py
compose/aws/url_generator.py
compose/command/__init__.py
compose/command/command.py
compose/dependency/__init__.py
compose/dependency/container.py
compose/dependency/provider.py
compose/dependency/wiring.py
compose/event/__init__.py
compose/event/event.py
compose/fastapi/__init__.py
compose/fastapi/depends.py
compose/fastapi/endpoint.py
compose/fastapi/exception_handler.py
compose/fastapi/openapi.py
compose/fastapi/otel.py
compose/fastapi/param.py
compose/fastapi/response.py
compose/fastapi/routing.py
compose/fastapi/security.py
compose/fastapi/utils.py
compose/fastapi/wiring.py
compose/gunicorn/__init__.py
compose/gunicorn/settings.py
compose/handler/__init__.py
compose/handler/mongo.py
compose/httpx/__init__.py
compose/httpx/auth/__init__.py
compose/httpx/auth/header.py
compose/lock/__init__.py
compose/lock/exceptions.py
compose/lock/mongo.py
compose/messaging/__init__.py
compose/messaging/consumer_runner.py
compose/messaging/messagebus.py
compose/messaging/model.py
compose/messaging/publisher.py
compose/messaging/signal_handler.py
compose/messaging/consumer/__init__.py
compose/messaging/consumer/fastapi.py
compose/messaging/consumer/general.py
compose/messaging/consumer/hook.py
compose/messaging/consumer/types.py
compose/messaging/queue/__init__.py
compose/messaging/queue/base.py
compose/messaging/queue/local.py
compose/messaging/queue/sqs.py
compose/monitoring/__init__.py
pozalabs_compose-1.35.0.dist-info/METADATA
pozalabs_compose-1.35.0.dist-info/WHEEL
pozalabs_compose-1.35.0.dist-info/licenses/LICENSE.md
pozalabs_compose-1.35.0.dist-info/RECORD
