Metadata-Version: 2.4
Name: pozalabs-compose
Version: 1.35.0
Summary: Backend components for Pozalabs
Author-email: sunwoong <sunwoong@pozalabs.com>, jeehoon <jeehoon@pozalabs.com>, soyeon <soyeon@pozalabs.com>, joowan <joowan@pozalabs.com>
License-Expression: MIT
License-File: LICENSE.md
Requires-Python: <3.14,>=3.12
Requires-Dist: authlib<2.0.0,>=1.3.1
Requires-Dist: dependency-injector<5.0.0,>=4.47.0
Requires-Dist: pendulum<4.0.0,>=3.1.0
Requires-Dist: pydantic-settings>=2.12.0
Requires-Dist: pydantic<3.0.0,>=2.7.4
Requires-Dist: pymongo[aws]<5.0.0,>=4.6.3
